halfapi/__init__.py
halfapi/__main__.py
halfapi/app.py
halfapi/conf.py
halfapi/half_domain.py
halfapi/half_route.py
halfapi/halfapi.py
halfapi/logging.py
halfapi/cli/__init__.py
halfapi/cli/cli.py
halfapi/cli/config.py
halfapi/cli/domain.py
halfapi/cli/init.py
halfapi/cli/routes.py
halfapi/cli/run.py
halfapi/lib/__init__.py
halfapi/lib/acl.py
halfapi/lib/constants.py
halfapi/lib/domain.py
halfapi/lib/domain_middleware.py
halfapi/lib/jwt_middleware.py
halfapi/lib/query.py
halfapi/lib/responses.py
halfapi/lib/router.py
halfapi/lib/routes.py
halfapi/lib/schemas.py
halfapi/lib/timing.py
halfapi/lib/user.py
halfapi/testing/__init__.py
halfapi/testing/test_domain.py
halfapi-0.7.0.dist-info/METADATA
halfapi-0.7.0.dist-info/WHEEL
halfapi-0.7.0.dist-info/entry_points.txt
halfapi-0.7.0.dist-info/top_level.txt
halfapi-0.7.0.dist-info/RECORD
