Metadata-Version: 2.1
Name: halfapi
Version: 0.7.0
Summary: Core to write deep APIs using a module's tree
Home-page: https://github.com/halfAPI/halfapi
Author: Maxime ALVES
Author-email: maxime@freepoteries.fr
License: GPLv3
Project-URL: Source, https://github.com/halfAPI/halfapi
Keywords: web-api development boilerplate
Classifier: Development Status :: 3 - Alpha
Classifier: License :: OSI Approved :: GNU General Public License v3 (GPLv3)
Classifier: Intended Audience :: Developers
Classifier: Topic :: Software Development :: Libraries :: Application Frameworks
Classifier: Programming Language :: Python :: 3.7
Classifier: Programming Language :: Python :: 3.8
Classifier: Programming Language :: Python :: 3.9
Classifier: Programming Language :: Python :: 3.10
Requires-Python: >=3.8
Requires-Dist: PyJWT (<2.7.0,>=2.6.0)
Requires-Dist: starlette (<0.24,>=0.23)
Requires-Dist: click (<9,>=8)
Requires-Dist: uvicorn (<1,>=0.13)
Requires-Dist: orjson (<4,>=3.8.5)
Requires-Dist: pyyaml (<7,>=6)
Requires-Dist: timing-asgi (<1,>=0.2.1)
Requires-Dist: schema (<1,>=0.7.4)
Requires-Dist: toml (<0.11,>=0.10)
Requires-Dist: packaging (>=19.0)
Requires-Dist: python-multipart
Provides-Extra: pyexcel
Requires-Dist: pyexcel ; extra == 'pyexcel'
Requires-Dist: pyexcel-ods3 ; extra == 'pyexcel'
Requires-Dist: pyexcel-xlsx ; extra == 'pyexcel'
Provides-Extra: tests
Requires-Dist: pytest (<8,>=7) ; extra == 'tests'
Requires-Dist: pytest-asyncio ; extra == 'tests'
Requires-Dist: pylint ; extra == 'tests'
Requires-Dist: requests ; extra == 'tests'
Requires-Dist: httpx ; extra == 'tests'
